[{"id_project":"connect","project":"Payzli Connect","id_environment":"production","id_buildable":6,"buildable":"Database","github_repository_url":"git@github.com:payzlicorp/connect.git","dt_inserted":"2023-11-29T16:18:57.297198+00:00","git_commit_hash":"b8f0d59a0cd40d9194af11f548d1594526bbc315","release_tag":"rls_14","version_text":"2.0.0","is_at_release":false,"github_run_id":7035437068}, 
 {"id_project":"connect","project":"Payzli Connect","id_environment":"production","id_buildable":7,"buildable":"Backend","github_repository_url":"git@github.com:payzlicorp/connect.git","dt_inserted":"2023-11-29T19:24:01.81203+00:00","git_commit_hash":"422b7238374191eb2129dfc26e7c3c7db1abc11a","release_tag":"rls_15","version_text":"2.0.1","is_at_release":false,"github_run_id":7037504967}, 
 {"id_project":"connect","project":"Payzli Connect","id_environment":"production","id_buildable":8,"buildable":"Frontend Web","github_repository_url":"git@github.com:payzlicorp/connect.git","dt_inserted":"2023-11-29T19:24:03.633062+00:00","git_commit_hash":"422b7238374191eb2129dfc26e7c3c7db1abc11a","release_tag":"rls_15","version_text":"2.0.1","is_at_release":false,"github_run_id":7037504967}, 
 {"id_project":"connect","project":"Payzli Connect","id_environment":"demo","id_buildable":6,"buildable":"Database","github_repository_url":"git@github.com:payzlicorp/connect.git","dt_inserted":"2023-12-01T13:33:32.916559+00:00","git_commit_hash":"b4b8de25c2aa5e6fb838b5c4e107a9c4cd6bb69d","release_tag":"rls_15","version_text":"2.1.0","is_at_release":false,"github_run_id":7060697013}, 
 {"id_project":"connect","project":"Payzli Connect","id_environment":"demo","id_buildable":7,"buildable":"Backend","github_repository_url":"git@github.com:payzlicorp/connect.git","dt_inserted":"2023-12-01T13:35:44.647578+00:00","git_commit_hash":"b4b8de25c2aa5e6fb838b5c4e107a9c4cd6bb69d","release_tag":"rls_15","version_text":"2.1.0","is_at_release":false,"github_run_id":7060697013}, 
 {"id_project":"connect","project":"Payzli Connect","id_environment":"demo","id_buildable":8,"buildable":"Frontend Web","github_repository_url":"git@github.com:payzlicorp/connect.git","dt_inserted":"2023-12-01T13:35:46.831269+00:00","git_commit_hash":"b4b8de25c2aa5e6fb838b5c4e107a9c4cd6bb69d","release_tag":"rls_15","version_text":"2.1.0","is_at_release":false,"github_run_id":7060697013}, 
 {"id_project":"connect","project":"Payzli Connect","id_environment":"qa","id_buildable":6,"buildable":"Database","github_repository_url":"git@github.com:payzlicorp/connect.git","dt_inserted":"2023-12-01T11:23:15.495521+00:00","git_commit_hash":"62d761244a5b8d309a2a01b877d573fca909b8cc","release_tag":"rls_15","version_text":"2.1.0","is_at_release":false,"github_run_id":7059373262}, 
 {"id_project":"connect","project":"Payzli Connect","id_environment":"qa","id_buildable":7,"buildable":"Backend","github_repository_url":"git@github.com:payzlicorp/connect.git","dt_inserted":"2023-12-01T12:59:36.82843+00:00","git_commit_hash":"1ded3b93eb114d8d07518510cf823525d40ba82f","release_tag":"rls_15","version_text":"2.1.0","is_at_release":false,"github_run_id":7060307572}, 
 {"id_project":"connect","project":"Payzli Connect","id_environment":"qa","id_buildable":8,"buildable":"Frontend Web","github_repository_url":"git@github.com:payzlicorp/connect.git","dt_inserted":"2023-12-01T12:59:39.498307+00:00","git_commit_hash":"1ded3b93eb114d8d07518510cf823525d40ba82f","release_tag":"rls_15","version_text":"2.1.0","is_at_release":false,"github_run_id":7060307572}, 
 {"id_project":"pos","project":"Payzli POS","id_environment":"production","id_buildable":3,"buildable":"Database","github_repository_url":"git@github.com:payzlicorp/pos.git","dt_inserted":"2023-12-06T04:35:52.528065+00:00","git_commit_hash":"7b14bc2fe61519b05c1849dfff5a01b088b4e1fd","release_tag":"rls_10","version_text":"1.1.4","is_at_release":true,"github_run_id":7110227756}, 
 {"id_project":"pos","project":"Payzli POS","id_environment":"production","id_buildable":2,"buildable":"Backend","github_repository_url":"git@github.com:payzlicorp/pos.git","dt_inserted":"2023-12-06T04:56:18.105499+00:00","git_commit_hash":"a018de1ddd458cfabd0a7a024060523cc3ab8c04","release_tag":"rls_10","version_text":"1.1.4","is_at_release":false,"github_run_id":7110331073}, 
 {"id_project":"pos","project":"Payzli POS","id_environment":"production","id_buildable":4,"buildable":"Frontend Web","github_repository_url":"git@github.com:payzlicorp/pos.git","dt_inserted":"2023-12-06T04:56:20.233425+00:00","git_commit_hash":"a018de1ddd458cfabd0a7a024060523cc3ab8c04","release_tag":"rls_10","version_text":"1.1.4","is_at_release":false,"github_run_id":7110331073}, 
 {"id_project":"pos","project":"Payzli POS","id_environment":"production","id_buildable":1,"buildable":"Frontend Android","github_repository_url":"git@github.com:payzlicorp/pos.git","dt_inserted":"2023-12-04T14:40:55.08343+00:00","git_commit_hash":"7b14bc2fe61519b05c1849dfff5a01b088b4e1fd","release_tag":"rls_10","version_text":"1.1.4","is_at_release":true,"github_run_id":7087973459}, 
 {"id_project":"pos","project":"Payzli POS","id_environment":"production","id_buildable":5,"buildable":"Frontend iOS","github_repository_url":"git@github.com:payzlicorp/pos.git","dt_inserted":"2023-11-30T09:58:18.754419+00:00","git_commit_hash":"0070229afe6ae33bc3688fbfaae4f4bb7e75802c","release_tag":"rls_9","version_text":"1.0.4","is_at_release":true,"github_run_id":7044557991}, 
 {"id_project":"pos","project":"Payzli POS","id_environment":"demo","id_buildable":3,"buildable":"Database","github_repository_url":"git@github.com:payzlicorp/pos.git","dt_inserted":"2023-11-21T08:28:23.909718+00:00","git_commit_hash":"bc3afa90f12f0d1026b6cdb2562b0bb3bc78550c","release_tag":"rls_5","version_text":"1.0.0","is_at_release":false,"github_run_id":6941150387}, 
 {"id_project":"pos","project":"Payzli POS","id_environment":"demo","id_buildable":2,"buildable":"Backend","github_repository_url":"git@github.com:payzlicorp/pos.git","dt_inserted":"2023-11-21T08:29:57.33056+00:00","git_commit_hash":"bc3afa90f12f0d1026b6cdb2562b0bb3bc78550c","release_tag":"rls_5","version_text":"1.0.0","is_at_release":false,"github_run_id":6941150387}, 
 {"id_project":"pos","project":"Payzli POS","id_environment":"demo","id_buildable":4,"buildable":"Frontend Web","github_repository_url":"git@github.com:payzlicorp/pos.git","dt_inserted":"2023-11-21T08:29:59.395171+00:00","git_commit_hash":"bc3afa90f12f0d1026b6cdb2562b0bb3bc78550c","release_tag":"rls_5","version_text":"1.0.0","is_at_release":false,"github_run_id":6941150387}, 
 {"id_project":"pos","project":"Payzli POS","id_environment":"demo","id_buildable":1,"buildable":"Frontend Android","github_repository_url":"git@github.com:payzlicorp/pos.git","dt_inserted":"2023-11-21T08:35:15.61752+00:00","git_commit_hash":"bc3afa90f12f0d1026b6cdb2562b0bb3bc78550c","release_tag":"rls_5","version_text":"1.0.0","is_at_release":false,"github_run_id":6941150387}, 
 {"id_project":"pos","project":"Payzli POS","id_environment":"demo","id_buildable":5,"buildable":"Frontend iOS","github_repository_url":"git@github.com:payzlicorp/pos.git","dt_inserted":"2023-11-21T08:49:42.382382+00:00","git_commit_hash":"bc3afa90f12f0d1026b6cdb2562b0bb3bc78550c","release_tag":"rls_5","version_text":"1.0.0","is_at_release":false,"github_run_id":6941150387}, 
 {"id_project":"pos","project":"Payzli POS","id_environment":"qa","id_buildable":3,"buildable":"Database","github_repository_url":"git@github.com:payzlicorp/pos.git","dt_inserted":"2023-12-06T07:26:01.452931+00:00","git_commit_hash":"02a043ee633607d21b674d3c017fc7865897a8cf","release_tag":"rls_11","version_text":"1.1.5","is_at_release":false,"github_run_id":7111462425}, 
 {"id_project":"pos","project":"Payzli POS","id_environment":"qa","id_buildable":2,"buildable":"Backend","github_repository_url":"git@github.com:payzlicorp/pos.git","dt_inserted":"2023-12-06T07:30:47.281087+00:00","git_commit_hash":"02a043ee633607d21b674d3c017fc7865897a8cf","release_tag":"rls_11","version_text":"1.1.5","is_at_release":false,"github_run_id":7111462425}, 
 {"id_project":"pos","project":"Payzli POS","id_environment":"qa","id_buildable":4,"buildable":"Frontend Web","github_repository_url":"git@github.com:payzlicorp/pos.git","dt_inserted":"2023-12-06T07:30:50.114833+00:00","git_commit_hash":"02a043ee633607d21b674d3c017fc7865897a8cf","release_tag":"rls_11","version_text":"1.1.5","is_at_release":false,"github_run_id":7111462425}, 
 {"id_project":"pos","project":"Payzli POS","id_environment":"qa","id_buildable":1,"buildable":"Frontend Android","github_repository_url":"git@github.com:payzlicorp/pos.git","dt_inserted":"2023-12-06T07:36:32.333638+00:00","git_commit_hash":"02a043ee633607d21b674d3c017fc7865897a8cf","release_tag":"rls_11","version_text":"1.1.5","is_at_release":false,"github_run_id":7111462425}, 
 {"id_project":"pos","project":"Payzli POS","id_environment":"qa","id_buildable":5,"buildable":"Frontend iOS","github_repository_url":"git@github.com:payzlicorp/pos.git","dt_inserted":"2023-12-04T06:46:36.985416+00:00","git_commit_hash":"1a0b2d8501bf737d300ed0ad058f989708c5d1b4","release_tag":"rls_9","version_text":"1.0.4","is_at_release":false,"github_run_id":7082854095}, 
 {"id_project":"ums","project":"UMS","id_environment":"production","id_buildable":9,"buildable":"Database","github_repository_url":"git@github.com:payzlicorp/ums.git","dt_inserted":"2023-10-17T05:22:08+00:00","git_commit_hash":"0328ee67393b28e269c23fefaa885b6a5e9be394","release_tag":null,"version_text":null,"is_at_release":false,"github_run_id":6542886900}, 
 {"id_project":"ums","project":"UMS","id_environment":"production","id_buildable":10,"buildable":"Backend","github_repository_url":"git@github.com:payzlicorp/ums.git","dt_inserted":"2023-11-14T06:13:09.360068+00:00","git_commit_hash":"93d8e5e04010a240ce5986f79d540be527e77b65","release_tag":null,"version_text":null,"is_at_release":false,"github_run_id":6859907899}, 
 {"id_project":"ums","project":"UMS","id_environment":"demo","id_buildable":9,"buildable":"Database","github_repository_url":"git@github.com:payzlicorp/ums.git","dt_inserted":"2023-10-16T16:19:43+00:00","git_commit_hash":"0328ee67393b28e269c23fefaa885b6a5e9be394","release_tag":null,"version_text":null,"is_at_release":false,"github_run_id":6536411103}, 
 {"id_project":"ums","project":"UMS","id_environment":"demo","id_buildable":10,"buildable":"Backend","github_repository_url":"git@github.com:payzlicorp/ums.git","dt_inserted":"2023-11-07T00:09:29+00:00","git_commit_hash":"f10bdfbbb2da8a1365bdcfbeaba7545624f58c1e","release_tag":null,"version_text":null,"is_at_release":false,"github_run_id":6778096211}, 
 {"id_project":"ums","project":"UMS","id_environment":"qa","id_buildable":9,"buildable":"Database","github_repository_url":"git@github.com:payzlicorp/ums.git","dt_inserted":"2023-10-13T12:40:47+00:00","git_commit_hash":"ede52cf5414240dad9392e2e02338218ae864a8c","release_tag":null,"version_text":null,"is_at_release":false,"github_run_id":6508345379}, 
 {"id_project":"ums","project":"UMS","id_environment":"qa","id_buildable":10,"buildable":"Backend","github_repository_url":"git@github.com:payzlicorp/ums.git","dt_inserted":"2023-11-04T17:17:24+00:00","git_commit_hash":"00fb696304f61b04c5ec98bdd37e92babbf6767c","release_tag":null,"version_text":null,"is_at_release":false,"github_run_id":6756193444}]
